loggen/__init__.py
loggen/__main__.py
loggen-1.2.1.dist-info/DESCRIPTION.rst
loggen-1.2.1.dist-info/METADATA
loggen-1.2.1.dist-info/RECORD
loggen-1.2.1.dist-info/WHEEL
loggen-1.2.1.dist-info/entry_points.txt
loggen-1.2.1.dist-info/metadata.json
loggen-1.2.1.dist-info/top_level.txt
