Metadata-Version: 2.0
Name: loggen
Version: 1.2.1
Summary: A syslog message generator.
Home-page: https://github.com/spack971/loggen
Author: Jimmy Thrasibule
Author-email: loggen@jimmy.lt
License: MIT
Keywords: syslog generator rfc5424 rfc3164
Platform: UNKNOWN
Classifier: License :: OSI Approved :: MIT License
Classifier: Development Status :: 5 - Production/Stable
Classifier: Environment :: Console
Classifier: Intended Audience :: Information Technology
Classifier: Intended Audience :: System Administrators
Classifier: Natural Language :: English
Classifier: Programming Language :: Python
Classifier: Programming Language :: Python :: 3
Classifier: Programming Language :: Python :: 3.6
Classifier: Programming Language :: Python :: Implementation :: CPython
Classifier: Operating System :: MacOS
Classifier: Operating System :: Microsoft :: Windows
Classifier: Operating System :: POSIX
Classifier: Topic :: System :: Logging
Classifier: Topic :: Utilities
Requires-Dist: rfc5424-logging-handler
Requires-Dist: semver
